Metadata-Version: 1.0
Name: thefuckPPPP
Version: 3.27
Summary: Magnificent app which corrects your previous console command
Home-page: https://github.com/nvbn/thefuck
Author: Vladimir Iakovlev
Author-email: nvbn.rm@gmail.com
License: MIT
Platform: UNKNOWN
